onion_location.py
onion_location-0.1.0.dist-info/METADATA
onion_location-0.1.0.dist-info/WHEEL
onion_location-0.1.0.dist-info/entry_points.txt
onion_location-0.1.0.dist-info/licenses/LICENSES/AGPL-3.0-or-later.md
onion_location-0.1.0.dist-info/licenses/LICENSES/CC0-1.0.txt
onion_location-0.1.0.dist-info/RECORD
